forex_data_extractor/__init__.py
forex_data_extractor/cli.py
forex_data_extractor/config.py
forex_data_extractor/export.py
forex_data_extractor/models.py
forex_data_extractor/scraper.py
forex_data_extractor/utils.py
forex_data_extractor-1.0.0.dist-info/METADATA
forex_data_extractor-1.0.0.dist-info/WHEEL
forex_data_extractor-1.0.0.dist-info/entry_points.txt
forex_data_extractor-1.0.0.dist-info/top_level.txt
forex_data_extractor-1.0.0.dist-info/RECORD
