Metadata-Version: 2.4
Name: forex-data-extractor
Version: 1.0.0
Summary: A tool for scraping historical forex data from Yahoo Finance
Home-page: https://github.com/yungKnight/forex_data_extractor
Author: kennery
Author-email: badoknight1@gmail.com
License: MIT
Project-URL: Bug Reports, https://github.com/yungKnight/forex_data_extractor/issues
Project-URL: Source, https://github.com/yungKnight/forex_data_extractor
Project-URL: Documentation, https://github.com/yungKnight/forex_data_extractor#readme
Keywords: forex,currency,financial-data,scraping,yahoo-finance,financial-data,currency,exchange-rates,historical-data,web-scraping,playwright
Platform: any
Classifier: Development Status :: 5 - Production/Stable
Classifier: Intended Audience :: Developers
Classifier: Intended Audience :: Financial and Insurance Industry
Classifier: License :: OSI Approved :: MIT License
Classifier: Operating System :: OS Independent
Classifier: Programming Language :: Python :: 3
Classifier: Programming Language :: Python :: 3.8
Classifier: Programming Language :: Python :: 3.9
Classifier: Programming Language :: Python :: 3.10
Classifier: Programming Language :: Python :: 3.11
Classifier: Programming Language :: Python :: 3.12
Classifier: Topic :: Office/Business :: Financial
Classifier: Topic :: Software Development :: Libraries :: Python Modules
Classifier: Topic :: Internet :: WWW/HTTP :: Dynamic Content
Classifier: Typing :: Typed
Requires-Python: >=3.8
Requires-Dist: annotated-types==0.7.0
Requires-Dist: attrs==25.3.0
Requires-Dist: Automat==25.4.16
Requires-Dist: certifi==2025.8.3
Requires-Dist: cffi==1.17.1
Requires-Dist: charset-normalizer==3.4.3
Requires-Dist: constantly==23.10.4
Requires-Dist: cryptography==45.0.6
Requires-Dist: cssselect==1.3.0
Requires-Dist: defusedxml==0.7.1
Requires-Dist: filelock==3.19.1
Requires-Dist: greenlet==3.2.4
Requires-Dist: hyperlink==21.0.0
Requires-Dist: idna==3.10
Requires-Dist: incremental==24.7.2
Requires-Dist: itemadapter==0.12.1
Requires-Dist: itemloaders==1.3.2
Requires-Dist: jmespath==1.0.1
Requires-Dist: lxml==6.0.1
Requires-Dist: packaging==25.0
Requires-Dist: parsel==1.10.0
Requires-Dist: playwright==1.54.0
Requires-Dist: Protego==0.5.0
Requires-Dist: pyasn1==0.6.1
Requires-Dist: pyasn1_modules==0.4.2
Requires-Dist: pycparser==2.22
Requires-Dist: pydantic==2.11.7
Requires-Dist: pydantic_core==2.33.2
Requires-Dist: PyDispatcher==2.0.7
Requires-Dist: pyee==13.0.0
Requires-Dist: pyOpenSSL==25.1.0
Requires-Dist: queuelib==1.8.0
Requires-Dist: requests==2.32.5
Requires-Dist: requests-file==2.1.0
Requires-Dist: Scrapy==2.13.3
Requires-Dist: scrapy-playwright==0.0.44
Requires-Dist: service-identity==24.2.0
Requires-Dist: setuptools==80.9.0
Requires-Dist: tldextract==5.3.0
Requires-Dist: Twisted==25.5.0
Requires-Dist: typing-inspection==0.4.1
Requires-Dist: typing_extensions==4.14.1
Requires-Dist: urllib3==2.5.0
Requires-Dist: w3lib==2.3.1
Requires-Dist: zope.interface==7.2
Dynamic: author
Dynamic: author-email
Dynamic: classifier
Dynamic: description
Dynamic: description-content-type
Dynamic: home-page
Dynamic: keywords
Dynamic: license
Dynamic: platform
Dynamic: project-url
Dynamic: requires-dist
Dynamic: requires-python
Dynamic: summary
